pi169/__init__.py
pi169/alpie_types.py
pi169/async_client.py
pi169/cli.py
pi169/client.py
pi169/exceptions.py
pi169-0.1.dist-info/METADATA
pi169-0.1.dist-info/WHEEL
pi169-0.1.dist-info/entry_points.txt
pi169-0.1.dist-info/top_level.txt
pi169-0.1.dist-info/RECORD
