Metadata-Version: 2.4
Name: pi169
Version: 0.1
Summary: Production-ready Python SDK for Alpie-Core, a 4-bit quantized 32B reasoning model achieving state-of-the-art efficiency and performance
Home-page: https://github.com/169Pi/Pi169-SDK
Author: 169PI
Author-email: support@169pi.com
License: Apache-2.0
Classifier: Development Status :: 4 - Beta
Classifier: Intended Audience :: Developers
Classifier: License :: OSI Approved :: MIT License
Classifier: Programming Language :: Python :: 3.10
Classifier: Programming Language :: Python :: 3.11
Classifier: Programming Language :: Python :: 3.12
Requires-Python: >=3.10
Requires-Dist: certifi>=2025.11.12
Requires-Dist: httpx>=0.28.1
Requires-Dist: httpcore>=1.0.9
Requires-Dist: h11>=0.16.0
Requires-Dist: idna>=3.11
Requires-Dist: sniffio>=1.3.1
Requires-Dist: packaging>=25.0
Requires-Dist: python-dotenv
Provides-Extra: dev
Requires-Dist: pytest>=9.0.1; extra == "dev"
Requires-Dist: pytest-mock>=3.15.1; extra == "dev"
Dynamic: author
Dynamic: author-email
Dynamic: classifier
Dynamic: description
Dynamic: description-content-type
Dynamic: home-page
Dynamic: license
Dynamic: provides-extra
Dynamic: requires-dist
Dynamic: requires-python
Dynamic: summary
